itk/Configuration/RTKConfig.py
itk/Configuration/RTK_snake_case.py
itk/RTKPython.py
itk/_RTKPython.so
itk/__init_rtk__.py
itk/itkContinuousIndexRTKPython.py
itk/itkCovariantVectorRTKPython.py
itk/itkCudaImageDataManagerRTKPython.py
itk/itkCudaImageRTKPython.py
itk/itkCudaImageToImageFilterRTKPython.py
itk/itkCudaInPlaceImageFilterRTKPython.py
itk/itkFixedArrayRTKPython.py
itk/itkImageBaseRTKPython.py
itk/itkImageDuplicatorRTKPython.py
itk/itkImageFileReaderRTKPython.py
itk/itkImageFileWriterRTKPython.py
itk/itkImageRTKPython.py
itk/itkImageRegionRTKPython.py
itk/itkImageSourceRTKPython.py
itk/itkImageToImageFilterRTKPython.py
itk/itkInPlaceImageFilterRTKPython.py
itk/itkMatrixRTKPython.py
itk/itkPointRTKPython.py
itk/itkPyBufferRTKPython.py
itk/itkVariableLengthVectorRTKPython.py
itk/itkVectorImageRTKPython.py
itk/itkVectorRTKPython.py
itk/itkWarpImageFilterRTKPython.py
itk/rtk3Doutputimage_group.py
itk/rtkADMMTotalVariationConeBeamReconstructionFilterPython.py
itk/rtkADMMWaveletsConeBeamReconstructionFilterPython.py
itk/rtkAmsterdamShroudImageFilterPython.py
itk/rtkBackProjectionImageFilterPython.py
itk/rtkBioscanGeometryReaderPython.py
itk/rtkBoellaardScatterCorrectionImageFilterPython.py
itk/rtkBoxShapePython.py
itk/rtkConditionalMedianImageFilterPython.py
itk/rtkConjugateGradientConeBeamReconstructionFilterPython.py
itk/rtkConstantImageSourcePython.py
itk/rtkConvexShapePython.py
itk/rtkCudaBackProjectionImageFilterPython.py
itk/rtkCudaConstantVolumeSourcePython.py
itk/rtkCudaDisplacedDetectorImageFilterPython.py
itk/rtkCudaFDKConeBeamReconstructionFilterPython.py
itk/rtkCudaFFTProjectionsConvolutionImageFilterPython.py
itk/rtkCudaFFTRampImageFilterPython.py
itk/rtkCudaForwardProjectionImageFilterPython.py
itk/rtkCudaIterativeFDKConeBeamReconstructionFilterPython.py
itk/rtkCudaParkerShortScanImageFilterPython.py
itk/rtkCudaScatterGlareCorrectionImageFilterPython.py
itk/rtkCudaSplatImageFilterPython.py
itk/rtkCyclicDeformationImageFilterPython.py
itk_rtk-2.7.0.post1.dist-info/METADATA
itk_rtk-2.7.0.post1.dist-info/WHEEL
itk_rtk-2.7.0.post1.dist-info/entry_points.txt
itk_rtk-2.7.0.post1.dist-info/licenses/LICENSE.TXT
itk_rtk-2.7.0.post1.dist-info/RECORD
